{"一般经营亏损": ["下滑", "下降", "负增长", "白干了", "跌跌不休", "亏损", "盈亏", "难题", "急需", "盈利难度大", "下调", "损失", "跌幅", "逆风", "不及预期", "拖累", "不乐观", "由盈转亏", "少于", "令人担忧", "巨亏", "变数", "大变局", "高风险", "喜忧参半", "首亏", "遭遇", "尴尬", "反差", "不合格", "微降"], "偿付": ["空缺", "难题", "缺陷", "通病", "缺席", "催促", "不足", "不透明", "不规范", "不到位", "变动", "意见不合", "缺位", "权利角逐", "罢免", "纷争", "亏损", "离职", "恶化", "恶性循环", "困境", "人员流失", "举步维艰", "不达标", "垃圾", "处罚", "损失", "性质恶劣", "漏洞", "风险", "缩减", "只减不增", "不履行", "难辞其咎", "重大声明", "撇干净", "流失", "反思", "浮出", "约谈", "监管函", "不合格", "下调", "违规", "隐患", "不理想", "乏力", "未达标", "迟迟", "减持", "下滑", "骤降", "退保", "缺口", "滑铁卢", "急剧", "滑坡", "人才流失", "最低水平", "不稳定", "严重受损", "严厉打击", "违法", "拒之门外", "排斥", "消耗", "压力", "一落千丈", "危机", "不景气", "凛冬", "失误", "下挫", "受挫", "放缓", "涉及", "长期不好", "盈亏", "困局", "借款", "跌至", "枯竭", "破产", "代价"], "公司治理": ["内斗", "私愤", "回击", "免职", "罢免", "分歧", "窃取", "破坏", "越权", "质疑", "独断专权", "违规", "矛盾", "执意", "妄行", "存疑", "私下", "独断专行", "包庇", "控诉", "索贿", "诬陷", "互怼", "扰乱", "不当行使职权", "指使", "流传", "解聘", "撒谎", "迟到", "早退", "矢口否认", "撕破脸", "走弯路", "效率低", "闹剧", "大幅调整", "将帅齐换", "个人原因", "引咎辞职", "生变", "股权清退", "揪出", "翻旧账", "清查", "不正当", "限制权利", "裁员", "打击", "危机", "惩治", "检查", "整改", "颠覆性", "虚挂", "铤而走险", "套取", "被罚", "震荡", "调查", "全面改整", "险资潜伏", "股权调整", "问责", "罚款", "双罚制", "乱象", "处罚", "监管意见", "滞纳", "解禁", "违约", "亏损", "债务危机", "重罚", "强制", "清出", "清退", "虚假材料", "隐瞒", "查处", "撤资"], "其他": ["顶包", "伪造", "疑点", "损失", "骗保", "烧毁"], "员工违法违纪": ["违反", "未按照", "未按约", "涉嫌", "违法", "处罚", "警告", "罚款", "涉案", "起诉", "勾结", "捏造", "诈骗", "作案", "伪造", "非法占有"], "外部风险": ["未按规定", "未标明价格", "瞒报", "虚报", "违反", "不真实", "虚假保单", "可疑", "未按照规定", "行政处罚", "硬伤", "不到位", "拒绝", "后果", "漏洞"], "服务不当": ["中途退出", "不完备", "不明确", "归属不当", "缺乏", "单一", "分类不当", "根本问题", "提供虚假资料", "搞错", "惊讶地发现", "脱保", "不一致", "误操作", "无法查询", "服务打折", "未给予满意答复", "质疑", "麻烦", "违法", "拉黑", "霸道", "拖延"], "流动性风险": ["耗尽", "终止", "缺失", "负担", "吃紧", "影响", "不占优势", "亏损", "困境", "堪忧", "流出", "不利", "不容乐观", "不达标", "缩水", "违规", "下滑"], "理赔纠纷": ["违规", "与实际不一致", "乱象", "未执行", "虚假", "损失", "有待", "不完善", "不完整", "不真实", "涉及赔案", "泛滥", "欺骗", "销售误导", "屡禁不止", "相悖", "重灾区", "积弊重重", "理赔难", "管控不力", "投诉", "骗取", "顶包", "骗保", "纠纷", "老大难", "拒赔"], "经营管理": ["不到位", "未按规定", "不规范", "不完全相符", "利益冲突", "不符合规定", "不相符", "不合规", "问题产品", "偏离", "盲目追求", "不合理", "不健全", "影响恶劣", "屡查屡犯", "不当", "未作明显标注", "不明确", "不完备", "背离", "损害", "责令", "整改", "受罚", "违规", "虚假报表", "虚假宣传", "大跌", "受限", "捏造", "存在问题", "虚构", "套取费用", "虚列", "违反", "罚款", "罚单", "未经许可", "屡发", "行政处罚", "遗失", "不依法履行", "不真实", "违法", "隐瞒"], "群体事件": ["群体对决", "质疑", "强烈不满", "抗议", "忧心忡忡", "纠纷", "牵扯", "情节严重"], "违规投资": ["违反", "处罚", "停牌", "违规", "转让", "撤销", "清退"], "重大案件": ["侵占", "涉嫌", "行贿", "纠纷", "破产", "重大案件", "罚款", "伪造", "假冒", "诈骗", "掩盖", "欺诈", "违法", "追责", "追究", "不满", "转让", "离谱", "涉案", "流出", "陷入", "风波", "被抓", "整改", "罚没", "罚单", "受罚", "重罚", "追债", "牵涉", "暴露", "勾结", "涉案"], "销售误导": ["问题", "违规", "不完全相符", "夸大", "虚假", "不实", "不规范", "乱象", "不如实告知", "不完全一致", "不符", "扰民", "欺骗", "误导", "隐瞒", "猫腻", "业绩平平", "下架", "非法", "重罚", "偏离", "停用", "失衡", "投诉", "纠纷", "不靠谱", "噱头", "混淆视听", "引诱", "冒用", "伪造", "强买强卖", "捆绑", "给投保人约定以外利益"], "高管违法违纪": ["涉嫌", "欺骗", "虚假", "伪造", "违反", "处罚", "罚款", "刑事诉讼", "违纪", "免职", "隐瞒", "严重警告", "撤销党内职务", "行政记过", "调离岗位", "公诉", "受贿", "审查", "职务便利", "非法", "谋取利益", "双开", "立案", "拉拢", "奢靡享乐", "收受", "严重情节", "贪污", "没收财产", "套取", "举报", "指控", "被诉", "追究", "索取", "谋取", "占为己有", "侵吞", "贪婪", "投机", "监察", "逮捕", "借款", "落马", "批捕"]}